[
  {
    "match_date": "2026-07-05",
    "fixture": {
      "fixture_id": 1568100,
      "date_utc": "2026-07-05T20:00:00+00:00",
      "status": "Not Started",
      "venue": "MetLife Stadium",
      "city": null,
      "league": "World Cup",
      "round": "Round of 16",
      "home_team": "Brazil",
      "away_team": "Norway",
      "goals_home": null,
      "goals_away": null
    },
    "prediction": {
      "available": true,
      "winner": {
        "id": 6,
        "name": "Brazil",
        "comment": "Win or draw"
      },
      "win_or_draw": true,
      "under_over": null,
      "goals": {
        "home": "-2.5",
        "away": "-3.5"
      },
      "advice": "Double chance : Brazil or draw",
      "win_probabilities": {
        "home": "35%",
        "draw": "35%",
        "away": "30%"
      },
      "comparison": {
        "form": {
          "home": "53%",
          "away": "47%"
        },
        "att": {
          "home": "47%",
          "away": "53%"
        },
        "def": {
          "home": "80%",
          "away": "20%"
        },
        "poisson_distribution": {
          "home": "39%",
          "away": "61%"
        },
        "h2h": {
          "home": "0%",
          "away": "0%"
        },
        "goals": {
          "home": "0%",
          "away": "0%"
        },
        "total": {
          "home": "54.8%",
          "away": "45.3%"
        }
      },
      "home_last5": {
        "form": "83%",
        "att": "69%",
        "def": "85%",
        "goals": {
          "for": {
            "total": 9,
            "average": "2.3"
          },
          "against": {
            "total": 2,
            "average": "0.5"
          }
        }
      },
      "away_last5": {
        "form": "75%",
        "att": "77%",
        "def": "38%",
        "goals": {
          "for": {
            "total": 10,
            "average": "2.5"
          },
          "against": {
            "total": 8,
            "average": "2.0"
          }
        }
      }
    }
  },
  {
    "match_date": "2026-07-06",
    "fixture": {
      "fixture_id": 1570714,
      "date_utc": "2026-07-06T00:00:00+00:00",
      "status": "Not Started",
      "venue": "Estadio Banorte",
      "city": "Mexico City",
      "league": "World Cup",
      "round": "Round of 16",
      "home_team": "Mexico",
      "away_team": "England",
      "goals_home": null,
      "goals_away": null
    },
    "prediction": {
      "available": true,
      "winner": {
        "id": 16,
        "name": "Mexico",
        "comment": "Win or draw"
      },
      "win_or_draw": true,
      "under_over": null,
      "goals": {
        "home": "-2.5",
        "away": "-2.5"
      },
      "advice": "Double chance : Mexico or draw",
      "win_probabilities": {
        "home": "45%",
        "draw": "45%",
        "away": "10%"
      },
      "comparison": {
        "form": {
          "home": "55%",
          "away": "45%"
        },
        "att": {
          "home": "50%",
          "away": "50%"
        },
        "def": {
          "home": "100%",
          "away": "0%"
        },
        "poisson_distribution": {
          "home": "0%",
          "away": "0%"
        },
        "h2h": {
          "home": "0%",
          "away": "0%"
        },
        "goals": {
          "home": "0%",
          "away": "0%"
        },
        "total": {
          "home": "52.5%",
          "away": "47.5%"
        }
      },
      "home_last5": {
        "form": "100%",
        "att": "67%",
        "def": "100%",
        "goals": {
          "for": {
            "total": 8,
            "average": "2.0"
          },
          "against": {
            "total": 0,
            "average": "0.0"
          }
        }
      },
      "away_last5": {
        "form": "83%",
        "att": "67%",
        "def": "75%",
        "goals": {
          "for": {
            "total": 8,
            "average": "2.0"
          },
          "against": {
            "total": 3,
            "average": "0.8"
          }
        }
      }
    }
  },
  {
    "match_date": "2026-07-06",
    "fixture": {
      "fixture_id": 1576756,
      "date_utc": "2026-07-06T19:00:00+00:00",
      "status": "Not Started",
      "venue": null,
      "city": null,
      "league": "World Cup",
      "round": "Round of 16",
      "home_team": "Portugal",
      "away_team": "Spain",
      "goals_home": null,
      "goals_away": null
    },
    "prediction": {
      "available": true,
      "winner": {
        "id": 9,
        "name": "Spain",
        "comment": "Win or draw"
      },
      "win_or_draw": true,
      "under_over": "-3.5",
      "goals": {
        "home": "-2.5",
        "away": "-2.5"
      },
      "advice": "Combo Double chance : draw or Spain and -3.5 goals",
      "win_probabilities": {
        "home": "10%",
        "draw": "45%",
        "away": "45%"
      },
      "comparison": {
        "form": {
          "home": "44%",
          "away": "56%"
        },
        "att": {
          "home": "50%",
          "away": "50%"
        },
        "def": {
          "home": "0%",
          "away": "100%"
        },
        "poisson_distribution": {
          "home": "0%",
          "away": "100%"
        },
        "h2h": {
          "home": "50%",
          "away": "50%"
        },
        "goals": {
          "home": "50%",
          "away": "50%"
        },
        "total": {
          "home": "48.5%",
          "away": "51.5%"
        }
      },
      "home_last5": {
        "form": "67%",
        "att": "67%",
        "def": "83%",
        "goals": {
          "for": {
            "total": 8,
            "average": "2.0"
          },
          "against": {
            "total": 2,
            "average": "0.5"
          }
        }
      },
      "away_last5": {
        "form": "83%",
        "att": "67%",
        "def": "100%",
        "goals": {
          "for": {
            "total": 8,
            "average": "2.0"
          },
          "against": {
            "total": 0,
            "average": "0.0"
          }
        }
      }
    }
  }
]