[
  {
    "match_date": "2026-06-27",
    "fixture": {
      "fixture_id": 1489417,
      "date_utc": "2026-06-27T00:00:00+00:00",
      "status": "Match Finished",
      "venue": "Estadio Akron",
      "city": "Zapopan",
      "league": "World Cup",
      "round": "Group Stage - 3",
      "home_team": "Uruguay",
      "away_team": "Spain",
      "goals_home": 0,
      "goals_away": 1
    },
    "prediction": {
      "available": true,
      "winner": {
        "id": 9,
        "name": "Spain",
        "comment": "Win or draw"
      },
      "win_or_draw": true,
      "under_over": null,
      "goals": {
        "home": "-2.5",
        "away": "-2.5"
      },
      "advice": "Double chance : draw or Spain",
      "win_probabilities": {
        "home": "10%",
        "draw": "45%",
        "away": "45%"
      },
      "comparison": {
        "form": {
          "home": "33%",
          "away": "67%"
        },
        "att": {
          "home": "43%",
          "away": "57%"
        },
        "def": {
          "home": "0%",
          "away": "100%"
        },
        "poisson_distribution": {
          "home": "0%",
          "away": "0%"
        },
        "h2h": {
          "home": "0%",
          "away": "100%"
        },
        "goals": {
          "home": "33%",
          "away": "67%"
        },
        "total": {
          "home": "36.3%",
          "away": "63.7%"
        }
      },
      "home_last5": {
        "form": "33%",
        "att": "18%",
        "def": "82%",
        "goals": {
          "for": {
            "total": 3,
            "average": "1.5"
          },
          "against": {
            "total": 3,
            "average": "1.5"
          }
        }
      },
      "away_last5": {
        "form": "67%",
        "att": "24%",
        "def": "100%",
        "goals": {
          "for": {
            "total": 4,
            "average": "2.0"
          },
          "against": {
            "total": 0,
            "average": "0.0"
          }
        }
      }
    }
  },
  {
    "match_date": "2026-06-27",
    "fixture": {
      "fixture_id": 1489413,
      "date_utc": "2026-06-27T00:00:00+00:00",
      "status": "Match Finished",
      "venue": "NRG Stadium",
      "city": "Houston",
      "league": "World Cup",
      "round": "Group Stage - 3",
      "home_team": "Cape Verde Islands",
      "away_team": "Saudi Arabia",
      "goals_home": 0,
      "goals_away": 0
    },
    "prediction": {
      "available": true,
      "winner": {
        "id": 1533,
        "name": "Cape Verde Islands",
        "comment": "Win or draw"
      },
      "win_or_draw": true,
      "under_over": null,
      "goals": {
        "home": "-1.5",
        "away": "-1.5"
      },
      "advice": "Double chance : Cape Verde Islands or draw",
      "win_probabilities": {
        "home": "50%",
        "draw": "50%",
        "away": "0%"
      },
      "comparison": {
        "form": {
          "home": "67%",
          "away": "33%"
        },
        "att": {
          "home": "67%",
          "away": "33%"
        },
        "def": {
          "home": "71%",
          "away": "29%"
        },
        "poisson_distribution": {
          "home": "0%",
          "away": "0%"
        },
        "h2h": {
          "home": "0%",
          "away": "0%"
        },
        "goals": {
          "home": "0%",
          "away": "0%"
        },
        "total": {
          "home": "68.3%",
          "away": "31.7%"
        }
      },
      "home_last5": {
        "form": "33%",
        "att": "12%",
        "def": "88%",
        "goals": {
          "for": {
            "total": 2,
            "average": "1.0"
          },
          "against": {
            "total": 2,
            "average": "1.0"
          }
        }
      },
      "away_last5": {
        "form": "17%",
        "att": "6%",
        "def": "71%",
        "goals": {
          "for": {
            "total": 1,
            "average": "0.5"
          },
          "against": {
            "total": 5,
            "average": "2.5"
          }
        }
      }
    }
  },
  {
    "match_date": "2026-06-27",
    "fixture": {
      "fixture_id": 1489414,
      "date_utc": "2026-06-27T03:00:00+00:00",
      "status": "Match Finished",
      "venue": "Lumen Field",
      "city": "Seattle",
      "league": "World Cup",
      "round": "Group Stage - 3",
      "home_team": "Egypt",
      "away_team": "Iran",
      "goals_home": 1,
      "goals_away": 1
    },
    "prediction": {
      "available": true,
      "winner": {
        "id": 32,
        "name": "Egypt",
        "comment": "Win or draw"
      },
      "win_or_draw": true,
      "under_over": null,
      "goals": {
        "home": "-2.5",
        "away": "-1.5"
      },
      "advice": "Double chance : Egypt or draw",
      "win_probabilities": {
        "home": "45%",
        "draw": "45%",
        "away": "10%"
      },
      "comparison": {
        "form": {
          "home": "67%",
          "away": "33%"
        },
        "att": {
          "home": "67%",
          "away": "33%"
        },
        "def": {
          "home": "50%",
          "away": "50%"
        },
        "poisson_distribution": {
          "home": "0%",
          "away": "0%"
        },
        "h2h": {
          "home": "0%",
          "away": "0%"
        },
        "goals": {
          "home": "0%",
          "away": "0%"
        },
        "total": {
          "home": "61.3%",
          "away": "38.7%"
        }
      },
      "home_last5": {
        "form": "67%",
        "att": "25%",
        "def": "88%",
        "goals": {
          "for": {
            "total": 4,
            "average": "2.0"
          },
          "against": {
            "total": 2,
            "average": "1.0"
          }
        }
      },
      "away_last5": {
        "form": "33%",
        "att": "13%",
        "def": "88%",
        "goals": {
          "for": {
            "total": 2,
            "average": "1.0"
          },
          "against": {
            "total": 2,
            "average": "1.0"
          }
        }
      }
    }
  },
  {
    "match_date": "2026-06-27",
    "fixture": {
      "fixture_id": 1489415,
      "date_utc": "2026-06-27T03:00:00+00:00",
      "status": "Match Finished",
      "venue": "BC Place",
      "city": "Vancouver",
      "league": "World Cup",
      "round": "Group Stage - 3",
      "home_team": "New Zealand",
      "away_team": "Belgium",
      "goals_home": 1,
      "goals_away": 5
    },
    "prediction": {
      "available": true,
      "winner": {
        "id": 1,
        "name": "Belgium",
        "comment": "Win or draw"
      },
      "win_or_draw": true,
      "under_over": null,
      "goals": {
        "home": "-2.5",
        "away": "-1.5"
      },
      "advice": "Double chance : draw or Belgium",
      "win_probabilities": {
        "home": "10%",
        "draw": "45%",
        "away": "45%"
      },
      "comparison": {
        "form": {
          "home": "33%",
          "away": "67%"
        },
        "att": {
          "home": "75%",
          "away": "25%"
        },
        "def": {
          "home": "17%",
          "away": "83%"
        },
        "poisson_distribution": {
          "home": "0%",
          "away": "0%"
        },
        "h2h": {
          "home": "50%",
          "away": "50%"
        },
        "goals": {
          "home": "0%",
          "away": "0%"
        },
        "total": {
          "home": "43.8%",
          "away": "56.3%"
        }
      },
      "home_last5": {
        "form": "17%",
        "att": "19%",
        "def": "69%",
        "goals": {
          "for": {
            "total": 3,
            "average": "1.5"
          },
          "against": {
            "total": 5,
            "average": "2.5"
          }
        }
      },
      "away_last5": {
        "form": "33%",
        "att": "6%",
        "def": "94%",
        "goals": {
          "for": {
            "total": 1,
            "average": "0.5"
          },
          "against": {
            "total": 1,
            "average": "0.5"
          }
        }
      }
    }
  },
  {
    "match_date": "2026-06-27",
    "fixture": {
      "fixture_id": 1489420,
      "date_utc": "2026-06-27T21:00:00+00:00",
      "status": "Not Started",
      "venue": "Lincoln Financial Field",
      "city": "Philadelphia",
      "league": "World Cup",
      "round": "Group Stage - 3",
      "home_team": "Croatia",
      "away_team": "Ghana",
      "goals_home": null,
      "goals_away": null
    },
    "prediction": {
      "available": true,
      "winner": {
        "id": 3,
        "name": "Croatia",
        "comment": "Win or draw"
      },
      "win_or_draw": true,
      "under_over": "-3.5",
      "goals": {
        "home": "-2.5",
        "away": "-1.5"
      },
      "advice": "Combo Double chance : Croatia or draw and -3.5 goals",
      "win_probabilities": {
        "home": "35%",
        "draw": "35%",
        "away": "30%"
      },
      "comparison": {
        "form": {
          "home": "43%",
          "away": "57%"
        },
        "att": {
          "home": "75%",
          "away": "25%"
        },
        "def": {
          "home": "0%",
          "away": "100%"
        },
        "poisson_distribution": {
          "home": "0%",
          "away": "0%"
        },
        "h2h": {
          "home": "0%",
          "away": "0%"
        },
        "goals": {
          "home": "0%",
          "away": "0%"
        },
        "total": {
          "home": "59.0%",
          "away": "41.0%"
        }
      },
      "home_last5": {
        "form": "50%",
        "att": "19%",
        "def": "75%",
        "goals": {
          "for": {
            "total": 3,
            "average": "1.5"
          },
          "against": {
            "total": 4,
            "average": "2.0"
          }
        }
      },
      "away_last5": {
        "form": "67%",
        "att": "6%",
        "def": "100%",
        "goals": {
          "for": {
            "total": 1,
            "average": "0.5"
          },
          "against": {
            "total": 0,
            "average": "0.0"
          }
        }
      }
    }
  },
  {
    "match_date": "2026-06-27",
    "fixture": {
      "fixture_id": 1489422,
      "date_utc": "2026-06-27T21:00:00+00:00",
      "status": "Not Started",
      "venue": "MetLife Stadium",
      "city": "New York New Jersey",
      "league": "World Cup",
      "round": "Group Stage - 3",
      "home_team": "Panama",
      "away_team": "England",
      "goals_home": null,
      "goals_away": null
    },
    "prediction": {
      "available": true,
      "winner": {
        "id": 10,
        "name": "England",
        "comment": null
      },
      "win_or_draw": false,
      "under_over": "-3.5",
      "goals": {
        "home": null,
        "away": "-2.5"
      },
      "advice": "Combo Winner : England and -3.5 goals",
      "win_probabilities": {
        "home": "10%",
        "draw": "45%",
        "away": "45%"
      },
      "comparison": {
        "form": {
          "home": "0%",
          "away": "100%"
        },
        "att": {
          "home": "0%",
          "away": "100%"
        },
        "def": {
          "home": "50%",
          "away": "50%"
        },
        "poisson_distribution": {
          "home": "0%",
          "away": "0%"
        },
        "h2h": {
          "home": "0%",
          "away": "100%"
        },
        "goals": {
          "home": "14%",
          "away": "86%"
        },
        "total": {
          "home": "32.0%",
          "away": "68.0%"
        }
      },
      "home_last5": {
        "form": "0%",
        "att": "0%",
        "def": "88%",
        "goals": {
          "for": {
            "total": 0,
            "average": "0.0"
          },
          "against": {
            "total": 2,
            "average": "1.0"
          }
        }
      },
      "away_last5": {
        "form": "67%",
        "att": "25%",
        "def": "88%",
        "goals": {
          "for": {
            "total": 4,
            "average": "2.0"
          },
          "against": {
            "total": 2,
            "average": "1.0"
          }
        }
      }
    }
  },
  {
    "match_date": "2026-06-27",
    "fixture": {
      "fixture_id": 1489419,
      "date_utc": "2026-06-27T23:30:00+00:00",
      "status": "Not Started",
      "venue": "Hard Rock Stadium",
      "city": "Miami",
      "league": "World Cup",
      "round": "Group Stage - 3",
      "home_team": "Colombia",
      "away_team": "Portugal",
      "goals_home": null,
      "goals_away": null
    },
    "prediction": {
      "available": true,
      "winner": {
        "id": 8,
        "name": "Colombia",
        "comment": "Win or draw"
      },
      "win_or_draw": true,
      "under_over": null,
      "goals": {
        "home": "-2.5",
        "away": "-3.5"
      },
      "advice": "Double chance : Colombia or draw",
      "win_probabilities": {
        "home": "35%",
        "draw": "35%",
        "away": "30%"
      },
      "comparison": {
        "form": {
          "home": "60%",
          "away": "40%"
        },
        "att": {
          "home": "40%",
          "away": "60%"
        },
        "def": {
          "home": "50%",
          "away": "50%"
        },
        "poisson_distribution": {
          "home": "0%",
          "away": "0%"
        },
        "h2h": {
          "home": "0%",
          "away": "0%"
        },
        "goals": {
          "home": "0%",
          "away": "0%"
        },
        "total": {
          "home": "50.0%",
          "away": "50.0%"
        }
      },
      "home_last5": {
        "form": "100%",
        "att": "25%",
        "def": "94%",
        "goals": {
          "for": {
            "total": 4,
            "average": "2.0"
          },
          "against": {
            "total": 1,
            "average": "0.5"
          }
        }
      },
      "away_last5": {
        "form": "67%",
        "att": "38%",
        "def": "94%",
        "goals": {
          "for": {
            "total": 6,
            "average": "3.0"
          },
          "against": {
            "total": 1,
            "average": "0.5"
          }
        }
      }
    }
  },
  {
    "match_date": "2026-06-27",
    "fixture": {
      "fixture_id": 1539013,
      "date_utc": "2026-06-27T23:30:00+00:00",
      "status": "Not Started",
      "venue": "Mercedes-Benz Stadium",
      "city": "Atlanta",
      "league": "World Cup",
      "round": "Group Stage - 3",
      "home_team": "Congo DR",
      "away_team": "Uzbekistan",
      "goals_home": null,
      "goals_away": null
    },
    "prediction": {
      "available": true,
      "winner": {
        "id": 1508,
        "name": "Congo DR",
        "comment": "Win or draw"
      },
      "win_or_draw": true,
      "under_over": null,
      "goals": {
        "home": "-1.5",
        "away": "-1.5"
      },
      "advice": "Double chance : Congo DR or draw",
      "win_probabilities": {
        "home": "45%",
        "draw": "45%",
        "away": "10%"
      },
      "comparison": {
        "form": {
          "home": "100%",
          "away": "0%"
        },
        "att": {
          "home": "50%",
          "away": "50%"
        },
        "def": {
          "home": "80%",
          "away": "20%"
        },
        "poisson_distribution": {
          "home": "0%",
          "away": "0%"
        },
        "h2h": {
          "home": "0%",
          "away": "0%"
        },
        "goals": {
          "home": "0%",
          "away": "0%"
        },
        "total": {
          "home": "65.0%",
          "away": "35.0%"
        }
      },
      "home_last5": {
        "form": "17%",
        "att": "6%",
        "def": "88%",
        "goals": {
          "for": {
            "total": 1,
            "average": "0.5"
          },
          "against": {
            "total": 2,
            "average": "1.0"
          }
        }
      },
      "away_last5": {
        "form": "0%",
        "att": "6%",
        "def": "50%",
        "goals": {
          "for": {
            "total": 1,
            "average": "0.5"
          },
          "against": {
            "total": 8,
            "average": "4.0"
          }
        }
      }
    }
  },
  {
    "match_date": "2026-06-28",
    "fixture": {
      "fixture_id": 1489418,
      "date_utc": "2026-06-28T02:00:00+00:00",
      "status": "Not Started",
      "venue": "Arrowhead Stadium",
      "city": "Kansas City",
      "league": "World Cup",
      "round": "Group Stage - 3",
      "home_team": "Algeria",
      "away_team": "Austria",
      "goals_home": null,
      "goals_away": null
    },
    "prediction": {
      "available": true,
      "winner": {
        "id": 775,
        "name": "Austria",
        "comment": "Win or draw"
      },
      "win_or_draw": true,
      "under_over": null,
      "goals": {
        "home": "-1.5",
        "away": "-2.5"
      },
      "advice": "Double chance : draw or Austria",
      "win_probabilities": {
        "home": "10%",
        "draw": "45%",
        "away": "45%"
      },
      "comparison": {
        "form": {
          "home": "50%",
          "away": "50%"
        },
        "att": {
          "home": "40%",
          "away": "60%"
        },
        "def": {
          "home": "43%",
          "away": "57%"
        },
        "poisson_distribution": {
          "home": "0%",
          "away": "0%"
        },
        "h2h": {
          "home": "0%",
          "away": "0%"
        },
        "goals": {
          "home": "0%",
          "away": "0%"
        },
        "total": {
          "home": "44.3%",
          "away": "55.7%"
        }
      },
      "home_last5": {
        "form": "50%",
        "att": "13%",
        "def": "75%",
        "goals": {
          "for": {
            "total": 2,
            "average": "1.0"
          },
          "against": {
            "total": 4,
            "average": "2.0"
          }
        }
      },
      "away_last5": {
        "form": "50%",
        "att": "19%",
        "def": "81%",
        "goals": {
          "for": {
            "total": 3,
            "average": "1.5"
          },
          "against": {
            "total": 3,
            "average": "1.5"
          }
        }
      }
    }
  },
  {
    "match_date": "2026-06-28",
    "fixture": {
      "fixture_id": 1489421,
      "date_utc": "2026-06-28T02:00:00+00:00",
      "status": "Not Started",
      "venue": "AT&T Stadium",
      "city": "Dallas",
      "league": "World Cup",
      "round": "Group Stage - 3",
      "home_team": "Jordan",
      "away_team": "Argentina",
      "goals_home": null,
      "goals_away": null
    },
    "prediction": {
      "available": true,
      "winner": {
        "id": 26,
        "name": "Argentina",
        "comment": null
      },
      "win_or_draw": false,
      "under_over": null,
      "goals": {
        "home": "-1.5",
        "away": "-3.5"
      },
      "advice": "Winner : Argentina",
      "win_probabilities": {
        "home": "0%",
        "draw": "50%",
        "away": "50%"
      },
      "comparison": {
        "form": {
          "home": "0%",
          "away": "100%"
        },
        "att": {
          "home": "29%",
          "away": "71%"
        },
        "def": {
          "home": "0%",
          "away": "100%"
        },
        "poisson_distribution": {
          "home": "0%",
          "away": "0%"
        },
        "h2h": {
          "home": "0%",
          "away": "0%"
        },
        "goals": {
          "home": "0%",
          "away": "0%"
        },
        "total": {
          "home": "29.0%",
          "away": "71.0%"
        }
      },
      "home_last5": {
        "form": "0%",
        "att": "13%",
        "def": "69%",
        "goals": {
          "for": {
            "total": 2,
            "average": "1.0"
          },
          "against": {
            "total": 5,
            "average": "2.5"
          }
        }
      },
      "away_last5": {
        "form": "100%",
        "att": "31%",
        "def": "100%",
        "goals": {
          "for": {
            "total": 5,
            "average": "2.5"
          },
          "against": {
            "total": 0,
            "average": "0.0"
          }
        }
      }
    }
  },
  {
    "match_date": "2026-06-28",
    "fixture": {
      "fixture_id": 1561329,
      "date_utc": "2026-06-28T19:00:00+00:00",
      "status": "Not Started",
      "venue": "SoFi Stadium",
      "city": null,
      "league": "World Cup",
      "round": "Round of 32",
      "home_team": "South Africa",
      "away_team": "Canada",
      "goals_home": null,
      "goals_away": null
    },
    "prediction": {
      "available": true,
      "winner": {
        "id": 1531,
        "name": "South Africa",
        "comment": "Win or draw"
      },
      "win_or_draw": true,
      "under_over": null,
      "goals": {
        "home": "-1.5",
        "away": "-3.5"
      },
      "advice": "Double chance : South Africa or draw",
      "win_probabilities": {
        "home": "35%",
        "draw": "35%",
        "away": "30%"
      },
      "comparison": {
        "form": {
          "home": "50%",
          "away": "50%"
        },
        "att": {
          "home": "20%",
          "away": "80%"
        },
        "def": {
          "home": "50%",
          "away": "50%"
        },
        "poisson_distribution": {
          "home": "100%",
          "away": "0%"
        },
        "h2h": {
          "home": "0%",
          "away": "0%"
        },
        "goals": {
          "home": "0%",
          "away": "0%"
        },
        "total": {
          "home": "40.0%",
          "away": "60.0%"
        }
      },
      "home_last5": {
        "form": "44%",
        "att": "14%",
        "def": "79%",
        "goals": {
          "for": {
            "total": 2,
            "average": "0.7"
          },
          "against": {
            "total": 3,
            "average": "1.0"
          }
        }
      },
      "away_last5": {
        "form": "44%",
        "att": "57%",
        "def": "79%",
        "goals": {
          "for": {
            "total": 8,
            "average": "2.7"
          },
          "against": {
            "total": 3,
            "average": "1.0"
          }
        }
      }
    }
  }
]